sdRDM/__init__.py
sdRDM/base/__init__.py
sdRDM/base/datamodel.py
sdRDM/base/datatypes/__init__.py
sdRDM/base/datatypes/unit.py
sdRDM/base/importedmodules.py
sdRDM/base/ioutils/__init__.py
sdRDM/base/ioutils/hdf5.py
sdRDM/base/listplus.py
sdRDM/base/referencecheck.py
sdRDM/base/tree.py
sdRDM/base/utils.py
sdRDM/cli.py
sdRDM/generator/__init__.py
sdRDM/generator/classrender.py
sdRDM/generator/codegen.py
sdRDM/generator/datatypes.py
sdRDM/generator/enumrender.py
sdRDM/generator/initrender.py
sdRDM/generator/schemagen.py
sdRDM/generator/templates/__init__.py
sdRDM/generator/templates/add_method_template.jinja2
sdRDM/generator/templates/add_unit_template.jinja2
sdRDM/generator/templates/attribute_leaf_template.jinja2
sdRDM/generator/templates/attribute_template.jinja2
sdRDM/generator/templates/class_template.jinja2
sdRDM/generator/templates/enum_template.jinja2
sdRDM/generator/templates/function_docstring.jinja2
sdRDM/generator/templates/import_template.jinja2
sdRDM/generator/templates/init_file_library.jinja2
sdRDM/generator/templates/init_file_template.jinja2
sdRDM/generator/templates/mermaid_class.jinja2
sdRDM/generator/templates/reference_template.jinja2
sdRDM/generator/updater.py
sdRDM/generator/utils.py
sdRDM/markdown/__init__.py
sdRDM/markdown/enumutils.py
sdRDM/markdown/markdownparser.py
sdRDM/markdown/objectutils.py
sdRDM/markdown/smalltypes.py
sdRDM/markdown/tokens.py
sdRDM/tools/__init__.py
sdRDM/tools/gitutils.py
sdRDM/tools/linker.py
sdRDM/tools/utils.py
sdrdm-0.2.3.dist-info/METADATA
sdrdm-0.2.3.dist-info/WHEEL
sdrdm-0.2.3.dist-info/entry_points.txt
sdrdm-0.2.3.dist-info/RECORD
