Metadata-Version: 2.1
Name: sdRDM
Version: 0.2.3
Summary: Software-driven RDM converts markdown data models into powerful objects that can be serialized to JSON, XML, YAML and HDF5
License: MIT
Author: Jan Range
Author-email: range.jan@web.de
Requires-Python: >=3.9,<4.0
Classifier: License :: OSI Approved :: MIT License
Classifier: Programming Language :: Python :: 3
Classifier: Programming Language :: Python :: 3.9
Classifier: Programming Language :: Python :: 3.10
Classifier: Programming Language :: Python :: 3.11
Classifier: Programming Language :: Python :: 3.12
Requires-Dist: anytree (>=2.12.1,<3.0.0)
Requires-Dist: astropy (>=6.0.0,<7.0.0)
Requires-Dist: autoflake (==2.0.0)
Requires-Dist: bigtree (>=0.15.4,<0.16.0)
Requires-Dist: black (>=23.12.1,<24.0.0)
Requires-Dist: dotted-dict (==1.1.3)
Requires-Dist: email-validator (>=2.1.0.post1,<3.0.0)
Requires-Dist: gitpython (>=3.1.41,<4.0.0)
Requires-Dist: jinja2 (>=3.1.3,<4.0.0)
Requires-Dist: lxml (>=5.1.0,<6.0.0)
Requires-Dist: markdown-it-py (>=3.0.0,<4.0.0)
Requires-Dist: nob (>=0.8.2,<0.9.0)
Requires-Dist: numpy (>=1.26.3,<2.0.0)
Requires-Dist: pandas (>=2.1.4,<3.0.0)
Requires-Dist: pydantic (>=2.6.0,<3.0.0)
Requires-Dist: pydantic-xml (>=2.9.0,<3.0.0)
Requires-Dist: python-frontmatter (>=1.1.0,<2.0.0)
Requires-Dist: pyyaml (>=6.0.1,<7.0.0)
Requires-Dist: rich (>=13.7.0,<14.0.0)
Requires-Dist: toml (>=0.10.2,<0.11.0)
Requires-Dist: typer (>=0.9.0,<0.10.0)
Requires-Dist: validators (>=0.22.0,<0.23.0)
